__init__.py
log_util.py
TCPLib/__init__.py
TCPLib/client_processor.py
TCPLib/message.py
TCPLib/tcp_client.py
TCPLib/tcp_server.py
TCPLib/utils.py
tcplib-2.0.2.dist-info/licenses/LICENSE
tcplib-2.0.2.dist-info/METADATA
tcplib-2.0.2.dist-info/WHEEL
tcplib-2.0.2.dist-info/top_level.txt
tcplib-2.0.2.dist-info/RECORD
