Metadata-Version: 2.4
Name: TCPLib
Version: 2.0.2
Summary: A basic library for implementing a TCP client/server
Author: Joshua Kitchen
License-Expression: MIT
Project-URL: Homepage, https://github.com/kitchej/TCPLib
Project-URL: Issues, https://github.com/kitchej/TCPLib/issues
Project-URL: Documentation, https://github.com/kitchej/TCPLib/blob/master/Documentation/docs.md
Classifier: Programming Language :: Python :: 3
Classifier: Operating System :: OS Independent
Requires-Python: >=3.10
License-File: LICENSE
Dynamic: license-file
